{
  "success": true,
  "totalCount": 19,
  "data": [
    {
      "id": 291666,
      "term": "202610",
      "termDesc": "Winter Quarter 2026",
      "courseReferenceNumber": "12202",
      "partOfTerm": "1",
      "courseNumber": "101",
      "courseDisplay": "101",
      "subject": "CYBR",
      "subjectDescription": "Cybersecurity",
      "sequenceNumber": "001",
      "campusDescription": "Cheney",
      "scheduleTypeDescription": "Lecture w Practice/Discussion",
      "courseTitle": "CYBERSECURITY FUNDAMENTALS",
      "creditHours": null,
      "maximumEnrollment": 40,
      "enrollment": 0,
      "seatsAvailable": 40,
      "waitCapacity": 5,
      "waitCount": 0,
      "waitAvailable": 5,
      "crossList": null,
      "crossListCapacity": null,
      "crossListCount": null,
      "crossListAvailable": null,
      "creditHourHigh": null,
      "creditHourLow": 5,
      "creditHourIndicator": null,
      "openSection": true,
      "linkIdentifier": null,
      "isSectionLinked": false,
      "subjectCourse": "CYBR101",
      "faculty": [
        {
          "bannerId": "1077",
          "category": null,
          "class": "net.hedtech.banner.student.faculty.FacultyResultDecorator",
          "courseReferenceNumber": "12202",
          "displayName": "Leachman, Eric",
          "emailAddress": "eleachman04@ewu.edu",
          "primaryIndicator": true,
          "term": "202610"
        },
        {
          "bannerId": "1078",
          "category": null,
          "class": "net.hedtech.banner.student.faculty.FacultyResultDecorator",
          "courseReferenceNumber": "12202",
          "displayName": "Rutherford, Robert",
          "emailAddress": "rrutherford3@ewu.edu",
          "primaryIndicator": false,
          "term": "202610"
        }
      ],
      "meetingsFaculty": [
        {
          "category": "01",
          "class": "net.hedtech.banner.student.schedule.SectionSessionDecorator",
          "courseReferenceNumber": "12202",
          "faculty": [],
          "meetingTime": {
            "beginTime": "0800",
            "building": "CEB",
            "buildingDescription": "Computer Engineering Bldg.",
            "campus": "CHN",
            "campusDescription": "Cheney",
            "category": "01",
            "class": "net.hedtech.banner.general.overall.MeetingTimeDecorator",
            "courseReferenceNumber": "12202",
            "creditHourSession": 5.0,
            "endDate": "03/20/2026",
            "endTime": "0850",
            "friday": true,
            "hoursWeek": 4.17,
            "meetingScheduleType": "LPD",
            "meetingType": "CLAS",
            "meetingTypeDescription": "Class",
            "monday": true,
            "room": "228",
            "saturday": false,
            "startDate": "01/05/2026",
            "sunday": false,
            "term": "202610",
            "thursday": true,
            "tuesday": true,
            "wednesday": true
          },
          "term": "202610"
        }
      ],
      "reservedSeatSummary": null,
      "sectionAttributes": [
        {
          "class": "net.hedtech.banner.student.schedule.SectionDegreeProgramAttributeDecorator",
          "code": "F011",
          "courseReferenceNumber": "12202",
          "description": "State Support Funding",
          "isZTCAttribute": false,
          "termCode": "202610"
        },
        {
          "class": "net.hedtech.banner.student.schedule.SectionDegreeProgramAttributeDecorator",
          "code": "GESS",
          "courseReferenceNumber": "12202",
          "description": "Social Science",
          "isZTCAttribute": false,
          "termCode": "202610"
        }
      ],
      "instructionalMethod": "F2F",
      "instructionalMethodDescription": "Face-to-Face"
    },
    {
      "id": 291667,
      "term": "202610",
      "termDesc": "Winter Quarter 2026",
      "courseReferenceNumber": "12203",
      "partOfTerm": "1",
      "courseNumber": "101",
      "courseDisplay": "101",
      "subject": "CYBR",
      "subjectDescription": "Cybersecurity",
      "sequenceNumber": "002",
      "campusDescription": "Cheney",
      "scheduleTypeDescription": "Lecture w Practice/Discussion",
      "courseTitle": "CYBERSECURITY FUNDAMENTALS",
      "creditHours": null,
      "maximumEnrollment": 40,
      "enrollment": 0,
      "seatsAvailable": 40,
      "waitCapacity": 5,
      "waitCount": 0,
      "waitAvailable": 5,
      "crossList": null,
      "crossListCapacity": null,
      "crossListCount": null,
      "crossListAvailable": null,
      "creditHourHigh": null,
      "creditHourLow": 5,
      "creditHourIndicator": null,
      "openSection": true,
      "linkIdentifier": null,
      "isSectionLinked": false,
      "subjectCourse": "CYBR101",
      "faculty": [
        {
          "bannerId": "1077",
          "category": null,
          "class": "net.hedtech.banner.student.faculty.FacultyResultDecorator",
          "courseReferenceNumber": "12203",
          "displayName": "Leachman, Eric",
          "emailAddress": "eleachman04@ewu.edu",
          "primaryIndicator": false,
          "term": "202610"
        },
        {
          "bannerId": "1078",
          "category": null,
          "class": "net.hedtech.banner.student.faculty.FacultyResultDecorator",
          "courseReferenceNumber": "12203",
          "displayName": "Rutherford, Robert",
          "emailAddress": "rrutherford3@ewu.edu",
          "primaryIndicator": true,
          "term": "202610"
        }
      ],
      "meetingsFaculty": [
        {
          "category": "01",
          "class": "net.hedtech.banner.student.schedule.SectionSessionDecorator",
          "courseReferenceNumber": "12203",
          "faculty": [],
          "meetingTime": {
            "beginTime": "0900",
            "building": "CEB",
            "buildingDescription": "Computer Engineering Bldg.",
            "campus": "CHN",
            "campusDescription": "Cheney",
            "category": "01",
            "class": "net.hedtech.banner.general.overall.MeetingTimeDecorator",
            "courseReferenceNumber": "12203",
            "creditHourSession": 5.0,
            "endDate": "03/20/2026",
            "endTime": "0950",
            "friday": true,
            "hoursWeek": 4.17,
            "meetingScheduleType": "LPD",
            "meetingType": "CLAS",
            "meetingTypeDescription": "Class",
            "monday": true,
            "room": "228",
            "saturday": false,
            "startDate": "01/05/2026",
            "sunday": false,
            "term": "202610",
            "thursday": true,
            "tuesday": true,
            "wednesday": true
          },
          "term": "202610"
        }
      ],
      "reservedSeatSummary": null,
      "sectionAttributes": [
        {
          "class": "net.hedtech.banner.student.schedule.SectionDegreeProgramAttributeDecorator",
          "code": "F011",
          "courseReferenceNumber": "12203",
          "description": "State Support Funding",
          "isZTCAttribute": false,
          "termCode": "202610"
        },
        {
          "class": "net.hedtech.banner.student.schedule.SectionDegreeProgramAttributeDecorator",
          "code": "GESS",
          "courseReferenceNumber": "12203",
          "description": "Social Science",
          "isZTCAttribute": false,
          "termCode": "202610"
        }
      ],
      "instructionalMethod": "F2F",
      "instructionalMethodDescription": "Face-to-Face"
    },
    {
      "id": 282068,
      "term": "202610",
      "termDesc": "Winter Quarter 2026",
      "courseReferenceNumber": "10622",
      "partOfTerm": "1",
      "courseNumber": "437",
      "courseDisplay": "437",
      "subject": "CYBR",
      "subjectDescription": "Cybersecurity",
      "sequenceNumber": "040",
      "campusDescription": "Spokane U-District",
      "scheduleTypeDescription": "Lecture with Corequisite Lab",
      "courseTitle": "SECURE CODING",
      "creditHours": null,
      "maximumEnrollment": 30,
      "enrollment": 0,
      "seatsAvailable": 30,
      "waitCapacity": 5,
      "waitCount": 0,
      "waitAvailable": 5,
      "crossList": "1A",
      "crossListCapacity": 38,
      "crossListCount": 0,
      "crossListAvailable": 38,
      "creditHourHigh": null,
      "creditHourLow": 3,
      "creditHourIndicator": null,
      "openSection": true,
      "linkIdentifier": null,
      "isSectionLinked": false,
      "subjectCourse": "CYBR437",
      "faculty": [
        {
          "bannerId": "996",
          "category": null,
          "class": "net.hedtech.banner.student.faculty.FacultyResultDecorator",
          "courseReferenceNumber": "10622",
          "displayName": "Borah, Abinash",
          "emailAddress": "aborah@ewu.edu",
          "primaryIndicator": true,
          "term": "202610"
        }
      ],
      "meetingsFaculty": [
        {
          "category": "01",
          "class": "net.hedtech.banner.student.schedule.SectionSessionDecorator",
          "courseReferenceNumber": "10622",
          "faculty": [],
          "meetingTime": {
            "beginTime": "1200",
            "building": "CAT",
            "buildingDescription": "Catalyst Building, Spokane",
            "campus": "RPT",
            "campusDescription": "Spokane U-District",
            "category": "01",
            "class": "net.hedtech.banner.general.overall.MeetingTimeDecorator",
            "courseReferenceNumber": "10622",
            "creditHourSession": 3.0,
            "endDate": "03/20/2026",
            "endTime": "1250",
            "friday": true,
            "hoursWeek": 2.5,
            "meetingScheduleType": "LEL",
            "meetingType": "CLAS",
            "meetingTypeDescription": "Class",
            "monday": true,
            "room": "221",
            "saturday": false,
            "startDate": "01/05/2026",
            "sunday": false,
            "term": "202610",
            "thursday": false,
            "tuesday": false,
            "wednesday": true
          },
          "term": "202610"
        }
      ],
      "reservedSeatSummary": null,
      "sectionAttributes": [
        {
          "class": "net.hedtech.banner.student.schedule.SectionDegreeProgramAttributeDecorator",
          "code": "F011",
          "courseReferenceNumber": "10622",
          "description": "State Support Funding",
          "isZTCAttribute": false,
          "termCode": "202610"
        }
      ],
      "instructionalMethod": "F2F",
      "instructionalMethodDescription": "Face-to-Face"
    },
    {
      "id": 282069,
      "term": "202610",
      "termDesc": "Winter Quarter 2026",
      "courseReferenceNumber": "10623",
      "partOfTerm": "1",
      "courseNumber": "437L",
      "courseDisplay": "437L",
      "subject": "CYBR",
      "subjectDescription": "Cybersecurity",
      "sequenceNumber": "040",
      "campusDescription": "Spokane U-District",
      "scheduleTypeDescription": "Laboratory",
      "courseTitle": "SECURE CODING LAB",
      "creditHours": null,
      "maximumEnrollment": 30,
      "enrollment": 0,
      "seatsAvailable": 30,
      "waitCapacity": 5,
      "waitCount": 0,
      "waitAvailable": 5,
      "crossList": "1E",
      "crossListCapacity": 38,
      "crossListCount": 0,
      "crossListAvailable": 38,
      "creditHourHigh": null,
      "creditHourLow": 1,
      "creditHourIndicator": null,
      "openSection": true,
      "linkIdentifier": null,
      "isSectionLinked": false,
      "subjectCourse": "CYBR437L",
      "faculty": [
        {
          "bannerId": "996",
          "category": null,
          "class": "net.hedtech.banner.student.faculty.FacultyResultDecorator",
          "courseReferenceNumber": "10623",
          "displayName": "Borah, Abinash",
          "emailAddress": "aborah@ewu.edu",
          "primaryIndicator": true,
          "term": "202610"
        }
      ],
      "meetingsFaculty": [
        {
          "category": "01",
          "class": "net.hedtech.banner.student.schedule.SectionSessionDecorator",
          "courseReferenceNumber": "10623",
          "faculty": [],
          "meetingTime": {
            "beginTime": "1300",
            "building": "CAT",
            "buildingDescription": "Catalyst Building, Spokane",
            "campus": "RPT",
            "campusDescription": "Spokane U-District",
            "category": "01",
            "class": "net.hedtech.banner.general.overall.MeetingTimeDecorator",
            "courseReferenceNumber": "10623",
            "creditHourSession": 1.0,
            "endDate": "03/20/2026",
            "endTime": "1450",
            "friday": false,
            "hoursWeek": 1.83,
            "meetingScheduleType": "LAB",
            "meetingType": "CLAS",
            "meetingTypeDescription": "Class",
            "monday": false,
            "room": "216",
            "saturday": false,
            "startDate": "01/05/2026",
            "sunday": false,
            "term": "202610",
            "thursday": false,
            "tuesday": true,
            "wednesday": false
          },
          "term": "202610"
        }
      ],
      "reservedSeatSummary": null,
      "sectionAttributes": [
        {
          "class": "net.hedtech.banner.student.schedule.SectionDegreeProgramAttributeDecorator",
          "code": "F011",
          "courseReferenceNumber": "10623",
          "description": "State Support Funding",
          "isZTCAttribute": false,
          "termCode": "202610"
        }
      ],
      "instructionalMethod": "F2F",
      "instructionalMethodDescription": "Face-to-Face"
    },
    {
      "id": 282070,
      "term": "202610",
      "termDesc": "Winter Quarter 2026",
      "courseReferenceNumber": "10624",
      "partOfTerm": "1",
      "courseNumber": "439",
      "courseDisplay": "439",
      "subject": "CYBR",
      "subjectDescription": "Cybersecurity",
      "sequenceNumber": "040",
      "campusDescription": "Spokane U-District",
      "scheduleTypeDescription": "Lecture with Corequisite Lab",
      "courseTitle": "CYBERSECURITY RISK ANALYSIS",
      "creditHours": 5,
      "maximumEnrollment": 30,
      "enrollment": 0,
      "seatsAvailable": 30,
      "waitCapacity": 5,
      "waitCount": 0,
      "waitAvailable": 5,
      "crossList": null,
      "crossListCapacity": null,
      "crossListCount": null,
      "crossListAvailable": null,
      "creditHourHigh": 5,
      "creditHourLow": 2,
      "creditHourIndicator": "TO",
      "openSection": true,
      "linkIdentifier": null,
      "isSectionLinked": false,
      "subjectCourse": "CYBR439",
      "faculty": [
        {
          "bannerId": "997",
          "category": null,
          "class": "net.hedtech.banner.student.faculty.FacultyResultDecorator",
          "courseReferenceNumber": "10624",
          "displayName": "Thurston, Karen",
          "emailAddress": "kthurston@ewu.edu",
          "primaryIndicator": true,
          "term": "202610"
        }
      ],
      "meetingsFaculty": [
        {
          "category": "01",
          "class": "net.hedtech.banner.student.schedule.SectionSessionDecorator",
          "courseReferenceNumber": "10624",
          "faculty": [],
          "meetingTime": {
            "beginTime": "1300",
            "building": "CAT",
            "buildingDescription": "Catalyst Building, Spokane",
            "campus": "RPT",
            "campusDescription": "Spokane U-District",
            "category": "01",
            "class": "net.hedtech.banner.general.overall.MeetingTimeDecorator",
            "courseReferenceNumber": "10624",
            "creditHourSession": 5.0,
            "endDate": "03/20/2026",
            "endTime": "1520",
            "friday": false,
            "hoursWeek": 4.67,
            "meetingScheduleType": "LEL",
            "meetingType": "CLAS",
            "meetingTypeDescription": "Class",
            "monday": true,
            "room": "215",
            "saturday": false,
            "startDate": "01/05/2026",
            "sunday": false,
            "term": "202610",
            "thursday": false,
            "tuesday": false,
            "wednesday": true
          },
          "term": "202610"
        }
      ],
      "reservedSeatSummary": null,
      "sectionAttributes": [
        {
          "class": "net.hedtech.banner.student.schedule.SectionDegreeProgramAttributeDecorator",
          "code": "F011",
          "courseReferenceNumber": "10624",
          "description": "State Support Funding",
          "isZTCAttribute": false,
          "termCode": "202610"
        }
      ],
      "instructionalMethod": "F2F",
      "instructionalMethodDescription": "Face-to-Face"
    },
    {
      "id": 286982,
      "term": "202610",
      "termDesc": "Winter Quarter 2026",
      "courseReferenceNumber": "11768",
      "partOfTerm": "1",
      "courseNumber": "445",
      "courseDisplay": "445",
      "subject": "CYBR",
      "subjectDescription": "Cybersecurity",
      "sequenceNumber": "040",
      "campusDescription": "Spokane U-District",
      "scheduleTypeDescription": "Lecture with Corequisite Lab",
      "courseTitle": "CRITICAL INFRASTRUCTURE SECURITY I",
      "creditHours": null,
      "maximumEnrollment": 20,
      "enrollment": 0,
      "seatsAvailable": 20,
      "waitCapacity": 2,
      "waitCount": 0,
      "waitAvailable": 2,
      "crossList": "5J",
      "crossListCapacity": 25,
      "crossListCount": 0,
      "crossListAvailable": 25,
      "creditHourHigh": null,
      "creditHourLow": 3,
      "creditHourIndicator": null,
      "openSection": true,
      "linkIdentifier": null,
      "isSectionLinked": false,
      "subjectCourse": "CYBR445",
      "faculty": [
        {
          "bannerId": "1076",
          "category": null,
          "class": "net.hedtech.banner.student.faculty.FacultyResultDecorator",
          "courseReferenceNumber": "11768",
          "displayName": "Walsh, Thomas",
          "emailAddress": "twalsh@ewu.edu",
          "primaryIndicator": true,
          "term": "202610"
        }
      ],
      "meetingsFaculty": [
        {
          "category": "01",
          "class": "net.hedtech.banner.student.schedule.SectionSessionDecorator",
          "courseReferenceNumber": "11768",
          "faculty": [],
          "meetingTime": {
            "beginTime": "1100",
            "building": "CAT",
            "buildingDescription": "Catalyst Building, Spokane",
            "campus": "RPT",
            "campusDescription": "Spokane U-District",
            "category": "01",
            "class": "net.hedtech.banner.general.overall.MeetingTimeDecorator",
            "courseReferenceNumber": "11768",
            "creditHourSession": 3.0,
            "endDate": "03/20/2026",
            "endTime": "1150",
            "friday": false,
            "hoursWeek": 2.5,
            "meetingScheduleType": "LEL",
            "meetingType": "CLAS",
            "meetingTypeDescription": "Class",
            "monday": true,
            "room": "214",
            "saturday": false,
            "startDate": "01/05/2026",
            "sunday": false,
            "term": "202610",
            "thursday": false,
            "tuesday": true,
            "wednesday": true
          },
          "term": "202610"
        }
      ],
      "reservedSeatSummary": null,
      "sectionAttributes": [
        {
          "class": "net.hedtech.banner.student.schedule.SectionDegreeProgramAttributeDecorator",
          "code": "F011",
          "courseReferenceNumber": "11768",
          "description": "State Support Funding",
          "isZTCAttribute": false,
          "termCode": "202610"
        }
      ],
      "instructionalMethod": "F2F",
      "instructionalMethodDescription": "Face-to-Face"
    },
    {
      "id": 286944,
      "term": "202610",
      "termDesc": "Winter Quarter 2026",
      "courseReferenceNumber": "11759",
      "partOfTerm": "1",
      "courseNumber": "445L",
      "courseDisplay": "445L",
      "subject": "CYBR",
      "subjectDescription": "Cybersecurity",
      "sequenceNumber": "040",
      "campusDescription": "Spokane U-District",
      "scheduleTypeDescription": "Laboratory",
      "courseTitle": "CRITICAL INFRASTRUCTURE SECURITY I LAB",
      "creditHours": null,
      "maximumEnrollment": 20,
      "enrollment": 0,
      "seatsAvailable": 20,
      "waitCapacity": 2,
      "waitCount": 0,
      "waitAvailable": 2,
      "crossList": "5H",
      "crossListCapacity": 25,
      "crossListCount": 0,
      "crossListAvailable": 25,
      "creditHourHigh": null,
      "creditHourLow": 1,
      "creditHourIndicator": null,
      "openSection": true,
      "linkIdentifier": null,
      "isSectionLinked": false,
      "subjectCourse": "CYBR445L",
      "faculty": [
        {
          "bannerId": "1076",
          "category": null,
          "class": "net.hedtech.banner.student.faculty.FacultyResultDecorator",
          "courseReferenceNumber": "11759",
          "displayName": "Walsh, Thomas",
          "emailAddress": "twalsh@ewu.edu",
          "primaryIndicator": true,
          "term": "202610"
        }
      ],
      "meetingsFaculty": [
        {
          "category": "01",
          "class": "net.hedtech.banner.student.schedule.SectionSessionDecorator",
          "courseReferenceNumber": "11759",
          "faculty": [],
          "meetingTime": {
            "beginTime": "1300",
            "building": "CAT",
            "buildingDescription": "Catalyst Building, Spokane",
            "campus": "RPT",
            "campusDescription": "Spokane U-District",
            "category": "01",
            "class": "net.hedtech.banner.general.overall.MeetingTimeDecorator",
            "courseReferenceNumber": "11759",
            "creditHourSession": 1.0,
            "endDate": "03/20/2026",
            "endTime": "1450",
            "friday": true,
            "hoursWeek": 1.83,
            "meetingScheduleType": "LAB",
            "meetingType": "CLAS",
            "meetingTypeDescription": "Class",
            "monday": false,
            "room": "193",
            "saturday": false,
            "startDate": "01/05/2026",
            "sunday": false,
            "term": "202610",
            "thursday": false,
            "tuesday": false,
            "wednesday": false
          },
          "term": "202610"
        }
      ],
      "reservedSeatSummary": null,
      "sectionAttributes": [
        {
          "class": "net.hedtech.banner.student.schedule.SectionDegreeProgramAttributeDecorator",
          "code": "F011",
          "courseReferenceNumber": "11759",
          "description": "State Support Funding",
          "isZTCAttribute": false,
          "termCode": "202610"
        }
      ],
      "instructionalMethod": "F2F",
      "instructionalMethodDescription": "Face-to-Face"
    },
    {
      "id": 282071,
      "term": "202610",
      "termDesc": "Winter Quarter 2026",
      "courseReferenceNumber": "10625",
      "partOfTerm": "1",
      "courseNumber": "463",
      "courseDisplay": "463",
      "subject": "CYBR",
      "subjectDescription": "Cybersecurity",
      "sequenceNumber": "040",
      "campusDescription": "Spokane U-District",
      "scheduleTypeDescription": "Lecture with Corequisite Lab",
      "courseTitle": "APPLIED CRYPTOGRAPHY",
      "creditHours": null,
      "maximumEnrollment": 15,
      "enrollment": 0,
      "seatsAvailable": 15,
      "waitCapacity": 2,
      "waitCount": 0,
      "waitAvailable": 2,
      "crossList": "1I",
      "crossListCapacity": 20,
      "crossListCount": 0,
      "crossListAvailable": 20,
      "creditHourHigh": null,
      "creditHourLow": 3,
      "creditHourIndicator": null,
      "openSection": true,
      "linkIdentifier": null,
      "isSectionLinked": false,
      "subjectCourse": "CYBR463",
      "faculty": [
        {
          "bannerId": "1035",
          "category": null,
          "class": "net.hedtech.banner.student.faculty.FacultyResultDecorator",
          "courseReferenceNumber": "10625",
          "displayName": "Kaur, Sanmeet",
          "emailAddress": "skaur20@ewu.edu",
          "primaryIndicator": true,
          "term": "202610"
        }
      ],
      "meetingsFaculty": [
        {
          "category": "01",
          "class": "net.hedtech.banner.student.schedule.SectionSessionDecorator",
          "courseReferenceNumber": "10625",
          "faculty": [],
          "meetingTime": {
            "beginTime": "0900",
            "building": "CAT",
            "buildingDescription": "Catalyst Building, Spokane",
            "campus": "RPT",
            "campusDescription": "Spokane U-District",
            "category": "01",
            "class": "net.hedtech.banner.general.overall.MeetingTimeDecorator",
            "courseReferenceNumber": "10625",
            "creditHourSession": 3.0,
            "endDate": "03/20/2026",
            "endTime": "0950",
            "friday": false,
            "hoursWeek": 2.5,
            "meetingScheduleType": "LEL",
            "meetingType": "CLAS",
            "meetingTypeDescription": "Class",
            "monday": true,
            "room": "221",
            "saturday": false,
            "startDate": "01/05/2026",
            "sunday": false,
            "term": "202610",
            "thursday": false,
            "tuesday": true,
            "wednesday": true
          },
          "term": "202610"
        }
      ],
      "reservedSeatSummary": null,
      "sectionAttributes": [
        {
          "class": "net.hedtech.banner.student.schedule.SectionDegreeProgramAttributeDecorator",
          "code": "F011",
          "courseReferenceNumber": "10625",
          "description": "State Support Funding",
          "isZTCAttribute": false,
          "termCode": "202610"
        }
      ],
      "instructionalMethod": "F2F",
      "instructionalMethodDescription": "Face-to-Face"
    },
    {
      "id": 282072,
      "term": "202610",
      "termDesc": "Winter Quarter 2026",
      "courseReferenceNumber": "10626",
      "partOfTerm": "1",
      "courseNumber": "463L",
      "courseDisplay": "463L",
      "subject": "CYBR",
      "subjectDescription": "Cybersecurity",
      "sequenceNumber": "040",
      "campusDescription": "Spokane U-District",
      "scheduleTypeDescription": "Laboratory",
      "courseTitle": "APPLIED CRYPTOGRAPHY LAB",
      "creditHours": null,
      "maximumEnrollment": 15,
      "enrollment": 0,
      "seatsAvailable": 15,
      "waitCapacity": 2,
      "waitCount": 0,
      "waitAvailable": 2,
      "crossList": "1M",
      "crossListCapacity": 20,
      "crossListCount": 0,
      "crossListAvailable": 20,
      "creditHourHigh": null,
      "creditHourLow": 1,
      "creditHourIndicator": null,
      "openSection": true,
      "linkIdentifier": null,
      "isSectionLinked": false,
      "subjectCourse": "CYBR463L",
      "faculty": [
        {
          "bannerId": "1035",
          "category": null,
          "class": "net.hedtech.banner.student.faculty.FacultyResultDecorator",
          "courseReferenceNumber": "10626",
          "displayName": "Kaur, Sanmeet",
          "emailAddress": "skaur20@ewu.edu",
          "primaryIndicator": true,
          "term": "202610"
        }
      ],
      "meetingsFaculty": [
        {
          "category": "01",
          "class": "net.hedtech.banner.student.schedule.SectionSessionDecorator",
          "courseReferenceNumber": "10626",
          "faculty": [],
          "meetingTime": {
            "beginTime": "1300",
            "building": "CAT",
            "buildingDescription": "Catalyst Building, Spokane",
            "campus": "RPT",
            "campusDescription": "Spokane U-District",
            "category": "01",
            "class": "net.hedtech.banner.general.overall.MeetingTimeDecorator",
            "courseReferenceNumber": "10626",
            "creditHourSession": 1.0,
            "endDate": "03/20/2026",
            "endTime": "1450",
            "friday": false,
            "hoursWeek": 1.83,
            "meetingScheduleType": "LAB",
            "meetingType": "CLAS",
            "meetingTypeDescription": "Class",
            "monday": false,
            "room": "193",
            "saturday": false,
            "startDate": "01/05/2026",
            "sunday": false,
            "term": "202610",
            "thursday": false,
            "tuesday": true,
            "wednesday": false
          },
          "term": "202610"
        }
      ],
      "reservedSeatSummary": null,
      "sectionAttributes": [
        {
          "class": "net.hedtech.banner.student.schedule.SectionDegreeProgramAttributeDecorator",
          "code": "F011",
          "courseReferenceNumber": "10626",
          "description": "State Support Funding",
          "isZTCAttribute": false,
          "termCode": "202610"
        }
      ],
      "instructionalMethod": "F2F",
      "instructionalMethodDescription": "Face-to-Face"
    },
    {
      "id": 282073,
      "term": "202610",
      "termDesc": "Winter Quarter 2026",
      "courseReferenceNumber": "10627",
      "partOfTerm": "1",
      "courseNumber": "487",
      "courseDisplay": "487",
      "subject": "CYBR",
      "subjectDescription": "Cybersecurity",
      "sequenceNumber": "004",
      "campusDescription": "Spokane U-District",
      "scheduleTypeDescription": "Lecture with Corequisite Lab",
      "courseTitle": "SECURE SOFTWARE ENGINEERING",
      "creditHours": null,
      "maximumEnrollment": 20,
      "enrollment": 0,
      "seatsAvailable": 20,
      "waitCapacity": 2,
      "waitCount": 0,
      "waitAvailable": 2,
      "crossList": null,
      "crossListCapacity": null,
      "crossListCount": null,
      "crossListAvailable": null,
      "creditHourHigh": null,
      "creditHourLow": 3,
      "creditHourIndicator": null,
      "openSection": true,
      "linkIdentifier": null,
      "isSectionLinked": false,
      "subjectCourse": "CYBR487",
      "faculty": [
        {
          "bannerId": "1075",
          "category": null,
          "class": "net.hedtech.banner.student.faculty.FacultyResultDecorator",
          "courseReferenceNumber": "10627",
          "displayName": "Espinoza, Antonio",
          "emailAddress": "aespinoza17@ewu.edu",
          "primaryIndicator": true,
          "term": "202610"
        }
      ],
      "meetingsFaculty": [
        {
          "category": "01",
          "class": "net.hedtech.banner.student.schedule.SectionSessionDecorator",
          "courseReferenceNumber": "10627",
          "faculty": [],
          "meetingTime": {
            "beginTime": "1000",
            "building": "CAT",
            "buildingDescription": "Catalyst Building, Spokane",
            "campus": "RPT",
            "campusDescription": "Spokane U-District",
            "category": "01",
            "class": "net.hedtech.banner.general.overall.MeetingTimeDecorator",
            "courseReferenceNumber": "10627",
            "creditHourSession": 3.0,
            "endDate": "03/20/2026",
            "endTime": "1050",
            "friday": false,
            "hoursWeek": 2.5,
            "meetingScheduleType": "LEL",
            "meetingType": "CLAS",
            "meetingTypeDescription": "Class",
            "monday": true,
            "room": "193",
            "saturday": false,
            "startDate": "01/05/2026",
            "sunday": false,
            "term": "202610",
            "thursday": false,
            "tuesday": true,
            "wednesday": true
          },
          "term": "202610"
        }
      ],
      "reservedSeatSummary": null,
      "sectionAttributes": [
        {
          "class": "net.hedtech.banner.student.schedule.SectionDegreeProgramAttributeDecorator",
          "code": "F011",
          "courseReferenceNumber": "10627",
          "description": "State Support Funding",
          "isZTCAttribute": false,
          "termCode": "202610"
        }
      ],
      "instructionalMethod": "F2F",
      "instructionalMethodDescription": "Face-to-Face"
    },
    {
      "id": 282074,
      "term": "202610",
      "termDesc": "Winter Quarter 2026",
      "courseReferenceNumber": "10628",
      "partOfTerm": "1",
      "courseNumber": "487L",
      "courseDisplay": "487L",
      "subject": "CYBR",
      "subjectDescription": "Cybersecurity",
      "sequenceNumber": "040",
      "campusDescription": "Spokane U-District",
      "scheduleTypeDescription": "Laboratory",
      "courseTitle": "SECURE SOFTWARE ENGINEERING LAB",
      "creditHours": null,
      "maximumEnrollment": 20,
      "enrollment": 0,
      "seatsAvailable": 20,
      "waitCapacity": 2,
      "waitCount": 0,
      "waitAvailable": 2,
      "crossList": null,
      "crossListCapacity": null,
      "crossListCount": null,
      "crossListAvailable": null,
      "creditHourHigh": null,
      "creditHourLow": 1,
      "creditHourIndicator": null,
      "openSection": true,
      "linkIdentifier": null,
      "isSectionLinked": false,
      "subjectCourse": "CYBR487L",
      "faculty": [
        {
          "bannerId": "1075",
          "category": null,
          "class": "net.hedtech.banner.student.faculty.FacultyResultDecorator",
          "courseReferenceNumber": "10628",
          "displayName": "Espinoza, Antonio",
          "emailAddress": "aespinoza17@ewu.edu",
          "primaryIndicator": true,
          "term": "202610"
        }
      ],
      "meetingsFaculty": [
        {
          "category": "01",
          "class": "net.hedtech.banner.student.schedule.SectionSessionDecorator",
          "courseReferenceNumber": "10628",
          "faculty": [],
          "meetingTime": {
            "beginTime": "1000",
            "building": "CAT",
            "buildingDescription": "Catalyst Building, Spokane",
            "campus": "RPT",
            "campusDescription": "Spokane U-District",
            "category": "01",
            "class": "net.hedtech.banner.general.overall.MeetingTimeDecorator",
            "courseReferenceNumber": "10628",
            "creditHourSession": 1.0,
            "endDate": "03/20/2026",
            "endTime": "1050",
            "friday": true,
            "hoursWeek": 1.67,
            "meetingScheduleType": "LAB",
            "meetingType": "CLAS",
            "meetingTypeDescription": "Class",
            "monday": false,
            "room": "193",
            "saturday": false,
            "startDate": "01/05/2026",
            "sunday": false,
            "term": "202610",
            "thursday": true,
            "tuesday": false,
            "wednesday": false
          },
          "term": "202610"
        }
      ],
      "reservedSeatSummary": null,
      "sectionAttributes": [
        {
          "class": "net.hedtech.banner.student.schedule.SectionDegreeProgramAttributeDecorator",
          "code": "F011",
          "courseReferenceNumber": "10628",
          "description": "State Support Funding",
          "isZTCAttribute": false,
          "termCode": "202610"
        }
      ],
      "instructionalMethod": "F2F",
      "instructionalMethodDescription": "Face-to-Face"
    },
    {
      "id": 282075,
      "term": "202610",
      "termDesc": "Winter Quarter 2026",
      "courseReferenceNumber": "10629",
      "partOfTerm": "1",
      "courseNumber": "535",
      "courseDisplay": "535",
      "subject": "CYBR",
      "subjectDescription": "Cybersecurity",
      "sequenceNumber": "040",
      "campusDescription": "Spokane U-District",
      "scheduleTypeDescription": "Lecture with Corequisite Lab",
      "courseTitle": "ADVANCED NETWORK SECURITY",
      "creditHours": null,
      "maximumEnrollment": 20,
      "enrollment": 0,
      "seatsAvailable": 20,
      "waitCapacity": 2,
      "waitCount": 0,
      "waitAvailable": 2,
      "crossList": null,
      "crossListCapacity": null,
      "crossListCount": null,
      "crossListAvailable": null,
      "creditHourHigh": null,
      "creditHourLow": 3,
      "creditHourIndicator": null,
      "openSection": true,
      "linkIdentifier": null,
      "isSectionLinked": false,
      "subjectCourse": "CYBR535",
      "faculty": [
        {
          "bannerId": "1075",
          "category": null,
          "class": "net.hedtech.banner.student.faculty.FacultyResultDecorator",
          "courseReferenceNumber": "10629",
          "displayName": "Espinoza, Antonio",
          "emailAddress": "aespinoza17@ewu.edu",
          "primaryIndicator": true,
          "term": "202610"
        }
      ],
      "meetingsFaculty": [
        {
          "category": "01",
          "class": "net.hedtech.banner.student.schedule.SectionSessionDecorator",
          "courseReferenceNumber": "10629",
          "faculty": [],
          "meetingTime": {
            "beginTime": "1300",
            "building": "CAT",
            "buildingDescription": "Catalyst Building, Spokane",
            "campus": "RPT",
            "campusDescription": "Spokane U-District",
            "category": "01",
            "class": "net.hedtech.banner.general.overall.MeetingTimeDecorator",
            "courseReferenceNumber": "10629",
            "creditHourSession": 3.0,
            "endDate": "03/20/2026",
            "endTime": "1450",
            "friday": false,
            "hoursWeek": 1.83,
            "meetingScheduleType": "LEL",
            "meetingType": "CLAS",
            "meetingTypeDescription": "Class",
            "monday": true,
            "room": "220",
            "saturday": false,
            "startDate": "01/05/2026",
            "sunday": false,
            "term": "202610",
            "thursday": false,
            "tuesday": false,
            "wednesday": false
          },
          "term": "202610"
        }
      ],
      "reservedSeatSummary": null,
      "sectionAttributes": [
        {
          "class": "net.hedtech.banner.student.schedule.SectionDegreeProgramAttributeDecorator",
          "code": "F011",
          "courseReferenceNumber": "10629",
          "description": "State Support Funding",
          "isZTCAttribute": false,
          "termCode": "202610"
        }
      ],
      "instructionalMethod": "F2F",
      "instructionalMethodDescription": "Face-to-Face"
    },
    {
      "id": 282076,
      "term": "202610",
      "termDesc": "Winter Quarter 2026",
      "courseReferenceNumber": "10630",
      "partOfTerm": "1",
      "courseNumber": "535L",
      "courseDisplay": "535L",
      "subject": "CYBR",
      "subjectDescription": "Cybersecurity",
      "sequenceNumber": "040",
      "campusDescription": "Spokane U-District",
      "scheduleTypeDescription": "Laboratory",
      "courseTitle": "ADVANCED NETWORK SECURITY LAB",
      "creditHours": null,
      "maximumEnrollment": 20,
      "enrollment": 0,
      "seatsAvailable": 20,
      "waitCapacity": 2,
      "waitCount": 0,
      "waitAvailable": 2,
      "crossList": null,
      "crossListCapacity": null,
      "crossListCount": null,
      "crossListAvailable": null,
      "creditHourHigh": null,
      "creditHourLow": 1,
      "creditHourIndicator": null,
      "openSection": true,
      "linkIdentifier": null,
      "isSectionLinked": false,
      "subjectCourse": "CYBR535L",
      "faculty": [
        {
          "bannerId": "1075",
          "category": null,
          "class": "net.hedtech.banner.student.faculty.FacultyResultDecorator",
          "courseReferenceNumber": "10630",
          "displayName": "Espinoza, Antonio",
          "emailAddress": "aespinoza17@ewu.edu",
          "primaryIndicator": true,
          "term": "202610"
        }
      ],
      "meetingsFaculty": [
        {
          "category": "01",
          "class": "net.hedtech.banner.student.schedule.SectionSessionDecorator",
          "courseReferenceNumber": "10630",
          "faculty": [],
          "meetingTime": {
            "beginTime": "1300",
            "building": "CAT",
            "buildingDescription": "Catalyst Building, Spokane",
            "campus": "RPT",
            "campusDescription": "Spokane U-District",
            "category": "01",
            "class": "net.hedtech.banner.general.overall.MeetingTimeDecorator",
            "courseReferenceNumber": "10630",
            "creditHourSession": 1.0,
            "endDate": "03/20/2026",
            "endTime": "1450",
            "friday": false,
            "hoursWeek": 1.83,
            "meetingScheduleType": "LAB",
            "meetingType": "CLAS",
            "meetingTypeDescription": "Class",
            "monday": false,
            "room": "193",
            "saturday": false,
            "startDate": "01/05/2026",
            "sunday": false,
            "term": "202610",
            "thursday": false,
            "tuesday": false,
            "wednesday": true
          },
          "term": "202610"
        }
      ],
      "reservedSeatSummary": null,
      "sectionAttributes": [
        {
          "class": "net.hedtech.banner.student.schedule.SectionDegreeProgramAttributeDecorator",
          "code": "F011",
          "courseReferenceNumber": "10630",
          "description": "State Support Funding",
          "isZTCAttribute": false,
          "termCode": "202610"
        }
      ],
      "instructionalMethod": "F2F",
      "instructionalMethodDescription": "Face-to-Face"
    },
    {
      "id": 282107,
      "term": "202610",
      "termDesc": "Winter Quarter 2026",
      "courseReferenceNumber": "10661",
      "partOfTerm": "1",
      "courseNumber": "537",
      "courseDisplay": "537",
      "subject": "CYBR",
      "subjectDescription": "Cybersecurity",
      "sequenceNumber": "040",
      "campusDescription": "Spokane U-District",
      "scheduleTypeDescription": "Lecture with Corequisite Lab",
      "courseTitle": "SECURE CODING",
      "creditHours": null,
      "maximumEnrollment": 8,
      "enrollment": 0,
      "seatsAvailable": 8,
      "waitCapacity": 2,
      "waitCount": 0,
      "waitAvailable": 2,
      "crossList": "1A",
      "crossListCapacity": 38,
      "crossListCount": 0,
      "crossListAvailable": 38,
      "creditHourHigh": null,
      "creditHourLow": 3,
      "creditHourIndicator": null,
      "openSection": true,
      "linkIdentifier": null,
      "isSectionLinked": false,
      "subjectCourse": "CYBR537",
      "faculty": [
        {
          "bannerId": "996",
          "category": null,
          "class": "net.hedtech.banner.student.faculty.FacultyResultDecorator",
          "courseReferenceNumber": "10661",
          "displayName": "Borah, Abinash",
          "emailAddress": "aborah@ewu.edu",
          "primaryIndicator": true,
          "term": "202610"
        }
      ],
      "meetingsFaculty": [
        {
          "category": "01",
          "class": "net.hedtech.banner.student.schedule.SectionSessionDecorator",
          "courseReferenceNumber": "10661",
          "faculty": [],
          "meetingTime": {
            "beginTime": "1200",
            "building": "CAT",
            "buildingDescription": "Catalyst Building, Spokane",
            "campus": "RPT",
            "campusDescription": "Spokane U-District",
            "category": "01",
            "class": "net.hedtech.banner.general.overall.MeetingTimeDecorator",
            "courseReferenceNumber": "10661",
            "creditHourSession": 3.0,
            "endDate": "03/20/2026",
            "endTime": "1250",
            "friday": true,
            "hoursWeek": 2.5,
            "meetingScheduleType": "LEL",
            "meetingType": "CLAS",
            "meetingTypeDescription": "Class",
            "monday": true,
            "room": "221",
            "saturday": false,
            "startDate": "01/05/2026",
            "sunday": false,
            "term": "202610",
            "thursday": false,
            "tuesday": false,
            "wednesday": true
          },
          "term": "202610"
        }
      ],
      "reservedSeatSummary": null,
      "sectionAttributes": [
        {
          "class": "net.hedtech.banner.student.schedule.SectionDegreeProgramAttributeDecorator",
          "code": "F011",
          "courseReferenceNumber": "10661",
          "description": "State Support Funding",
          "isZTCAttribute": false,
          "termCode": "202610"
        }
      ],
      "instructionalMethod": "F2F",
      "instructionalMethodDescription": "Face-to-Face"
    },
    {
      "id": 282108,
      "term": "202610",
      "termDesc": "Winter Quarter 2026",
      "courseReferenceNumber": "10662",
      "partOfTerm": "1",
      "courseNumber": "537L",
      "courseDisplay": "537L",
      "subject": "CYBR",
      "subjectDescription": "Cybersecurity",
      "sequenceNumber": "040",
      "campusDescription": "Spokane U-District",
      "scheduleTypeDescription": "Laboratory",
      "courseTitle": "SECURE CODING LAB",
      "creditHours": null,
      "maximumEnrollment": 8,
      "enrollment": 0,
      "seatsAvailable": 8,
      "waitCapacity": 2,
      "waitCount": 0,
      "waitAvailable": 2,
      "crossList": "1E",
      "crossListCapacity": 38,
      "crossListCount": 0,
      "crossListAvailable": 38,
      "creditHourHigh": null,
      "creditHourLow": 1,
      "creditHourIndicator": null,
      "openSection": true,
      "linkIdentifier": null,
      "isSectionLinked": false,
      "subjectCourse": "CYBR537L",
      "faculty": [
        {
          "bannerId": "996",
          "category": null,
          "class": "net.hedtech.banner.student.faculty.FacultyResultDecorator",
          "courseReferenceNumber": "10662",
          "displayName": "Borah, Abinash",
          "emailAddress": "aborah@ewu.edu",
          "primaryIndicator": true,
          "term": "202610"
        }
      ],
      "meetingsFaculty": [
        {
          "category": "01",
          "class": "net.hedtech.banner.student.schedule.SectionSessionDecorator",
          "courseReferenceNumber": "10662",
          "faculty": [],
          "meetingTime": {
            "beginTime": "1300",
            "building": "CAT",
            "buildingDescription": "Catalyst Building, Spokane",
            "campus": "RPT",
            "campusDescription": "Spokane U-District",
            "category": "01",
            "class": "net.hedtech.banner.general.overall.MeetingTimeDecorator",
            "courseReferenceNumber": "10662",
            "creditHourSession": 1.0,
            "endDate": "03/20/2026",
            "endTime": "1450",
            "friday": false,
            "hoursWeek": 1.83,
            "meetingScheduleType": "LAB",
            "meetingType": "CLAS",
            "meetingTypeDescription": "Class",
            "monday": false,
            "room": "216",
            "saturday": false,
            "startDate": "01/05/2026",
            "sunday": false,
            "term": "202610",
            "thursday": false,
            "tuesday": true,
            "wednesday": false
          },
          "term": "202610"
        }
      ],
      "reservedSeatSummary": null,
      "sectionAttributes": [
        {
          "class": "net.hedtech.banner.student.schedule.SectionDegreeProgramAttributeDecorator",
          "code": "F011",
          "courseReferenceNumber": "10662",
          "description": "State Support Funding",
          "isZTCAttribute": false,
          "termCode": "202610"
        }
      ],
      "instructionalMethod": "F2F",
      "instructionalMethodDescription": "Face-to-Face"
    },
    {
      "id": 291475,
      "term": "202610",
      "termDesc": "Winter Quarter 2026",
      "courseReferenceNumber": "12192",
      "partOfTerm": "1",
      "courseNumber": "545",
      "courseDisplay": "545",
      "subject": "CYBR",
      "subjectDescription": "Cybersecurity",
      "sequenceNumber": "040",
      "campusDescription": "Spokane U-District",
      "scheduleTypeDescription": "Lecture with Corequisite Lab",
      "courseTitle": "CRITICAL INFRASTRUCTURE SECURITY I",
      "creditHours": null,
      "maximumEnrollment": 5,
      "enrollment": 0,
      "seatsAvailable": 5,
      "waitCapacity": 2,
      "waitCount": 0,
      "waitAvailable": 2,
      "crossList": "5J",
      "crossListCapacity": 25,
      "crossListCount": 0,
      "crossListAvailable": 25,
      "creditHourHigh": null,
      "creditHourLow": 3,
      "creditHourIndicator": null,
      "openSection": true,
      "linkIdentifier": null,
      "isSectionLinked": false,
      "subjectCourse": "CYBR545",
      "faculty": [
        {
          "bannerId": "1076",
          "category": null,
          "class": "net.hedtech.banner.student.faculty.FacultyResultDecorator",
          "courseReferenceNumber": "12192",
          "displayName": "Walsh, Thomas",
          "emailAddress": "twalsh@ewu.edu",
          "primaryIndicator": true,
          "term": "202610"
        }
      ],
      "meetingsFaculty": [
        {
          "category": "01",
          "class": "net.hedtech.banner.student.schedule.SectionSessionDecorator",
          "courseReferenceNumber": "12192",
          "faculty": [],
          "meetingTime": {
            "beginTime": "1100",
            "building": "CAT",
            "buildingDescription": "Catalyst Building, Spokane",
            "campus": "RPT",
            "campusDescription": "Spokane U-District",
            "category": "01",
            "class": "net.hedtech.banner.general.overall.MeetingTimeDecorator",
            "courseReferenceNumber": "12192",
            "creditHourSession": 3.0,
            "endDate": "03/20/2026",
            "endTime": "1150",
            "friday": false,
            "hoursWeek": 2.5,
            "meetingScheduleType": "LEL",
            "meetingType": "CLAS",
            "meetingTypeDescription": "Class",
            "monday": true,
            "room": "214",
            "saturday": false,
            "startDate": "01/05/2026",
            "sunday": false,
            "term": "202610",
            "thursday": false,
            "tuesday": true,
            "wednesday": true
          },
          "term": "202610"
        }
      ],
      "reservedSeatSummary": null,
      "sectionAttributes": [
        {
          "class": "net.hedtech.banner.student.schedule.SectionDegreeProgramAttributeDecorator",
          "code": "F011",
          "courseReferenceNumber": "12192",
          "description": "State Support Funding",
          "isZTCAttribute": false,
          "termCode": "202610"
        }
      ],
      "instructionalMethod": "F2F",
      "instructionalMethodDescription": "Face-to-Face"
    },
    {
      "id": 291474,
      "term": "202610",
      "termDesc": "Winter Quarter 2026",
      "courseReferenceNumber": "12191",
      "partOfTerm": "1",
      "courseNumber": "545L",
      "courseDisplay": "545L",
      "subject": "CYBR",
      "subjectDescription": "Cybersecurity",
      "sequenceNumber": "040",
      "campusDescription": "Spokane U-District",
      "scheduleTypeDescription": "Laboratory",
      "courseTitle": "CRITICAL INFRASTRUCTURE SECURITY I LAB",
      "creditHours": null,
      "maximumEnrollment": 5,
      "enrollment": 0,
      "seatsAvailable": 5,
      "waitCapacity": 2,
      "waitCount": 0,
      "waitAvailable": 2,
      "crossList": "5H",
      "crossListCapacity": 25,
      "crossListCount": 0,
      "crossListAvailable": 25,
      "creditHourHigh": null,
      "creditHourLow": 1,
      "creditHourIndicator": null,
      "openSection": true,
      "linkIdentifier": null,
      "isSectionLinked": false,
      "subjectCourse": "CYBR545L",
      "faculty": [
        {
          "bannerId": "1076",
          "category": null,
          "class": "net.hedtech.banner.student.faculty.FacultyResultDecorator",
          "courseReferenceNumber": "12191",
          "displayName": "Walsh, Thomas",
          "emailAddress": "twalsh@ewu.edu",
          "primaryIndicator": true,
          "term": "202610"
        }
      ],
      "meetingsFaculty": [
        {
          "category": "01",
          "class": "net.hedtech.banner.student.schedule.SectionSessionDecorator",
          "courseReferenceNumber": "12191",
          "faculty": [],
          "meetingTime": {
            "beginTime": "1300",
            "building": "CAT",
            "buildingDescription": "Catalyst Building, Spokane",
            "campus": "RPT",
            "campusDescription": "Spokane U-District",
            "category": "01",
            "class": "net.hedtech.banner.general.overall.MeetingTimeDecorator",
            "courseReferenceNumber": "12191",
            "creditHourSession": 1.0,
            "endDate": "03/20/2026",
            "endTime": "1450",
            "friday": true,
            "hoursWeek": 1.83,
            "meetingScheduleType": "LAB",
            "meetingType": "CLAS",
            "meetingTypeDescription": "Class",
            "monday": false,
            "room": "193",
            "saturday": false,
            "startDate": "01/05/2026",
            "sunday": false,
            "term": "202610",
            "thursday": false,
            "tuesday": false,
            "wednesday": false
          },
          "term": "202610"
        }
      ],
      "reservedSeatSummary": null,
      "sectionAttributes": [
        {
          "class": "net.hedtech.banner.student.schedule.SectionDegreeProgramAttributeDecorator",
          "code": "F011",
          "courseReferenceNumber": "12191",
          "description": "State Support Funding",
          "isZTCAttribute": false,
          "termCode": "202610"
        }
      ],
      "instructionalMethod": "F2F",
      "instructionalMethodDescription": "Face-to-Face"
    },
    {
      "id": 282109,
      "term": "202610",
      "termDesc": "Winter Quarter 2026",
      "courseReferenceNumber": "10663",
      "partOfTerm": "1",
      "courseNumber": "563",
      "courseDisplay": "563",
      "subject": "CYBR",
      "subjectDescription": "Cybersecurity",
      "sequenceNumber": "040",
      "campusDescription": "Spokane U-District",
      "scheduleTypeDescription": "Lecture with Corequisite Lab",
      "courseTitle": "APPLIED CRYPTOGRAPHY",
      "creditHours": null,
      "maximumEnrollment": 5,
      "enrollment": 0,
      "seatsAvailable": 5,
      "waitCapacity": 2,
      "waitCount": 0,
      "waitAvailable": 2,
      "crossList": "1I",
      "crossListCapacity": 20,
      "crossListCount": 0,
      "crossListAvailable": 20,
      "creditHourHigh": null,
      "creditHourLow": 3,
      "creditHourIndicator": null,
      "openSection": true,
      "linkIdentifier": null,
      "isSectionLinked": false,
      "subjectCourse": "CYBR563",
      "faculty": [
        {
          "bannerId": "1035",
          "category": null,
          "class": "net.hedtech.banner.student.faculty.FacultyResultDecorator",
          "courseReferenceNumber": "10663",
          "displayName": "Kaur, Sanmeet",
          "emailAddress": "skaur20@ewu.edu",
          "primaryIndicator": true,
          "term": "202610"
        }
      ],
      "meetingsFaculty": [
        {
          "category": "01",
          "class": "net.hedtech.banner.student.schedule.SectionSessionDecorator",
          "courseReferenceNumber": "10663",
          "faculty": [],
          "meetingTime": {
            "beginTime": "0900",
            "building": "CAT",
            "buildingDescription": "Catalyst Building, Spokane",
            "campus": "RPT",
            "campusDescription": "Spokane U-District",
            "category": "01",
            "class": "net.hedtech.banner.general.overall.MeetingTimeDecorator",
            "courseReferenceNumber": "10663",
            "creditHourSession": 3.0,
            "endDate": "03/20/2026",
            "endTime": "0950",
            "friday": false,
            "hoursWeek": 2.5,
            "meetingScheduleType": "LEL",
            "meetingType": "CLAS",
            "meetingTypeDescription": "Class",
            "monday": true,
            "room": "221",
            "saturday": false,
            "startDate": "01/05/2026",
            "sunday": false,
            "term": "202610",
            "thursday": false,
            "tuesday": true,
            "wednesday": true
          },
          "term": "202610"
        }
      ],
      "reservedSeatSummary": null,
      "sectionAttributes": [
        {
          "class": "net.hedtech.banner.student.schedule.SectionDegreeProgramAttributeDecorator",
          "code": "F011",
          "courseReferenceNumber": "10663",
          "description": "State Support Funding",
          "isZTCAttribute": false,
          "termCode": "202610"
        }
      ],
      "instructionalMethod": "F2F",
      "instructionalMethodDescription": "Face-to-Face"
    },
    {
      "id": 282110,
      "term": "202610",
      "termDesc": "Winter Quarter 2026",
      "courseReferenceNumber": "10664",
      "partOfTerm": "1",
      "courseNumber": "563L",
      "courseDisplay": "563L",
      "subject": "CYBR",
      "subjectDescription": "Cybersecurity",
      "sequenceNumber": "040",
      "campusDescription": "Spokane U-District",
      "scheduleTypeDescription": "Laboratory",
      "courseTitle": "APPLIED CRYPTOGRAPHY LAB",
      "creditHours": null,
      "maximumEnrollment": 5,
      "enrollment": 0,
      "seatsAvailable": 5,
      "waitCapacity": 2,
      "waitCount": 0,
      "waitAvailable": 2,
      "crossList": "1M",
      "crossListCapacity": 20,
      "crossListCount": 0,
      "crossListAvailable": 20,
      "creditHourHigh": null,
      "creditHourLow": 1,
      "creditHourIndicator": null,
      "openSection": true,
      "linkIdentifier": null,
      "isSectionLinked": false,
      "subjectCourse": "CYBR563L",
      "faculty": [
        {
          "bannerId": "1035",
          "category": null,
          "class": "net.hedtech.banner.student.faculty.FacultyResultDecorator",
          "courseReferenceNumber": "10664",
          "displayName": "Kaur, Sanmeet",
          "emailAddress": "skaur20@ewu.edu",
          "primaryIndicator": true,
          "term": "202610"
        }
      ],
      "meetingsFaculty": [
        {
          "category": "01",
          "class": "net.hedtech.banner.student.schedule.SectionSessionDecorator",
          "courseReferenceNumber": "10664",
          "faculty": [],
          "meetingTime": {
            "beginTime": "1300",
            "building": "CAT",
            "buildingDescription": "Catalyst Building, Spokane",
            "campus": "RPT",
            "campusDescription": "Spokane U-District",
            "category": "01",
            "class": "net.hedtech.banner.general.overall.MeetingTimeDecorator",
            "courseReferenceNumber": "10664",
            "creditHourSession": 1.0,
            "endDate": "03/20/2026",
            "endTime": "1450",
            "friday": false,
            "hoursWeek": 1.83,
            "meetingScheduleType": "LAB",
            "meetingType": "CLAS",
            "meetingTypeDescription": "Class",
            "monday": false,
            "room": "193",
            "saturday": false,
            "startDate": "01/05/2026",
            "sunday": false,
            "term": "202610",
            "thursday": false,
            "tuesday": true,
            "wednesday": false
          },
          "term": "202610"
        }
      ],
      "reservedSeatSummary": null,
      "sectionAttributes": [
        {
          "class": "net.hedtech.banner.student.schedule.SectionDegreeProgramAttributeDecorator",
          "code": "F011",
          "courseReferenceNumber": "10664",
          "description": "State Support Funding",
          "isZTCAttribute": false,
          "termCode": "202610"
        }
      ],
      "instructionalMethod": "F2F",
      "instructionalMethodDescription": "Face-to-Face"
    }
  ],
  "pageOffset": 0,
  "pageMaxSize": 100,
  "sectionsFetchedCount": 19,
  "pathMode": "search",
  "searchResultsConfigs": null
}
